data/.gitignore
data/README.md
data/publish-all-runs-of-team.py
data/update-leaderboard.py
data/rank-distillm/README.md
data/rank-distillm/config.json
data/rank-distillm/dataset-metadata.json
data/rank-distillm/dataset-metadata.yml
data/rank-distillm/rank_distillm.py
data/rank-distillm/subsample.json
data/trec-18-web/README.md
data/trec-18-web/config.json
data/trec-18-web/dataset-metadata.json
data/trec-18-web/dataset-metadata.yml
data/trec-18-web/subsample.json
data/trec-19-web/README.md
data/trec-19-web/config.json
data/trec-19-web/dataset-metadata.json
data/trec-19-web/dataset-metadata.yml
data/trec-19-web/subsample.json
data/trec-20-web/README.md
data/trec-20-web/config.json
data/trec-20-web/dataset-metadata.json
data/trec-20-web/dataset-metadata.yml
data/trec-20-web/subsample.json
data/trec-21-web/README.md
data/trec-21-web/config.json
data/trec-21-web/dataset-metadata.json
data/trec-21-web/dataset-metadata.yml
data/trec-21-web/subsample.json
data/trec-22-web/README.md
data/trec-22-web/config.json
data/trec-22-web/dataset-metadata.json
data/trec-22-web/dataset-metadata.yml
data/trec-22-web/subsample.json
data/trec-23-web/README.md
data/trec-23-web/config.json
data/trec-23-web/dataset-metadata.json
data/trec-23-web/dataset-metadata.yml
data/trec-23-web/subsample.json
data/trec-28-deep-learning-docs/config.json
data/trec-28-deep-learning-docs/subsample.json
data/trec-28-deep-learning-passages/README.md
data/trec-28-deep-learning-passages/config.json
data/trec-28-deep-learning-passages/dataset-metadata.json
data/trec-28-deep-learning-passages/dataset-metadata.yml
data/trec-28-deep-learning-passages/subsample.json
data/trec-28-misinfo/README.md
data/trec-28-misinfo/config.json
data/trec-28-misinfo/dataset-metadata.json
data/trec-28-misinfo/dataset-metadata.yml
data/trec-28-misinfo/subsample.json
data/trec-29-deep-learning-docs/config.json
data/trec-29-deep-learning-docs/subsample.json
data/trec-29-deep-learning-passages/README.md
lsr_benchmark-0.1.0.dist-info/licenses/LICENSE
lsr_benchmark-0.1.0.dist-info/METADATA
lsr_benchmark-0.1.0.dist-info/WHEEL
lsr_benchmark-0.1.0.dist-info/entry_points.txt
lsr_benchmark-0.1.0.dist-info/top_level.txt
lsr_benchmark-0.1.0.dist-info/RECORD
