Metadata-Version: 2.4
Name: lsr-benchmark
Version: 0.1.0
Summary: The lsr-benchmark aims to support holistic evaluations of the lexical sparse retrieval paradigm to contrast efficiency and effectiveness across diverse retrieval scenarios.
Author: Cosimo Rulli, Gijs Hendriksen, Carlos Lassance, Franco Maria Nardini, Rossano Venturini
Author-email: Maik Fröbe <maik.froebe@uni-jena.de>, Ferdinand Schlatt <ferdinand.schlatt@uni-jena.de>, Tim Hagen <tim.hagen@uni-kassel.de>, Jan Heinrich Merker <heinrich.merker@uni-jena.de>, Martin Potthast <martin.potthast@uni-kassel.de>
License-Expression: MIT
Project-URL: Homepage, https://github.com/reneuir/lsr-benchmark
Project-URL: Bug Tracker, https://github.com/reneuir/lsr-benchmark/issues
Classifier: Programming Language :: Python :: 3
Classifier: Programming Language :: Python :: 3 :: Only
Classifier: Programming Language :: Python :: 3.9
Classifier: Programming Language :: Python :: 3.10
Classifier: Programming Language :: Python :: 3.11
Classifier: Programming Language :: Python :: 3.12
Classifier: Programming Language :: Python :: 3.13
Classifier: Operating System :: OS Independent
Classifier: Intended Audience :: Science/Research
Classifier: Topic :: Scientific/Engineering
Requires-Python: >=3.9
License-File: LICENSE
Requires-Dist: click
Requires-Dist: ir-datasets
Requires-Dist: ir-measures
Requires-Dist: pyyaml
Requires-Dist: tira
Requires-Dist: tirex-tracker~=0.2.18
Requires-Dist: tqdm
Provides-Extra: test
Requires-Dist: approvaltests; extra == "test"
Requires-Dist: evaluate; extra == "test"
Requires-Dist: parameterized; extra == "test"
Requires-Dist: pyterrier~=1.0; extra == "test"
Requires-Dist: pytest~=8.0; extra == "test"
Requires-Dist: pytest-cov~=5.0; extra == "test"
Requires-Dist: ruff~=0.13.1; extra == "test"
Requires-Dist: spacy~=3.8; extra == "test"
Requires-Dist: trectools; extra == "test"
Provides-Extra: dev
Requires-Dist: spacy~=3.8; extra == "dev"
Requires-Dist: trectools; extra == "dev"
Dynamic: license-file
